gtsystem/__init__.py
gtsystem/anthropic.py
gtsystem/bedrock.py
gtsystem/chat.py
gtsystem/groq.py
gtsystem/leaderboard.py
gtsystem/ollama.py
gtsystem/openai.py
gtsystem/render.py
gtsystem/tasks.py
gtsystem-0.3.1.dist-info/METADATA
gtsystem-0.3.1.dist-info/WHEEL
gtsystem-0.3.1.dist-info/licenses/LICENSE
gtsystem-0.3.1.dist-info/RECORD
